{"/_app":"pages/_app.js","/_error":"pages/_error.js","/api/ViewQuestions":"pages/api/ViewQuestions.js","/api/allposts":"pages/api/allposts.js","/api/beginnerQuestions":"pages/api/beginnerQuestions.js","/api/contact":"pages/api/contact.js","/api/forgot-password":"pages/api/forgot-password.js","/api/getpostanswers":"pages/api/getpostanswers.js","/api/login":"pages/api/login.js","/api/postanswer":"pages/api/postanswer.js","/api/postdelete":"pages/api/postdelete.js","/api/posts":"pages/api/posts.js","/api/profile":"pages/api/profile.js","/api/resend-otp":"pages/api/resend-otp.js","/api/reset-password":"pages/api/reset-password.js","/api/showposts":"pages/api/showposts.js","/api/signup":"pages/api/signup.js","/api/solved-questions-monthly":"pages/api/solved-questions-monthly.js","/api/user-initial":"pages/api/user-initial.js","/api/verify-otp":"pages/api/verify-otp.js","/_document":"pages/_document.js","/404":"pages/404.html"}